config/__init__.py
config/asgi.py
config/settings.py
config/urls.py
config/wsgi.py
djrest_wrapper/__init__.py
djrest_wrapper/apps.py
djrest_wrapper/middlewares.py
djrest_wrapper/decorators/__init__.py
djrest_wrapper/decorators/create_model.py
djrest_wrapper/decorators/delete_model.py
djrest_wrapper/decorators/list_model.py
djrest_wrapper/decorators/retrieve_model.py
djrest_wrapper/decorators/serializer_validation.py
djrest_wrapper/decorators/update_model.py
djrest_wrapper/exceptions/__init__.py
djrest_wrapper/exceptions/handler.py
djrest_wrapper/exceptions/apis/__init__.py
djrest_wrapper/exceptions/apis/base.py
djrest_wrapper/exceptions/apis/errors.py
djrest_wrapper/exceptions/apis/exceptions.py
djrest_wrapper/exceptions/services/__init__.py
djrest_wrapper/exceptions/services/base.py
djrest_wrapper/exceptions/services/exceptions.py
djrest_wrapper/interfaces/__init__.py
djrest_wrapper/interfaces/basemodel.py
djrest_wrapper/interfaces/baseservice.py
djrest_wrapper/interfaces/baseviewset.py
djrest_wrapper/interfaces/mixins.py
djrest_wrapper/paginations/__init__.py
djrest_wrapper/paginations/default.py
djrest_wrapper/permissions/__init__.py
djrest_wrapper/permissions/base.py
djrest_wrapper/permissions/permissions.py
djrest_wrapper/renderers/__init__.py
djrest_wrapper/renderers/defaultjson.py
tests/__init__.py
tests/apps.py
tests/models.py
tests/serializers.py
tests/service.py
tests/test_model.py
tests/test_service.py
tests/test_views.py
tests/urls.py
tests/views.py
djrest_wrapper-0.3.0.dist-info/LICENSE
djrest_wrapper-0.3.0.dist-info/METADATA
djrest_wrapper-0.3.0.dist-info/WHEEL
djrest_wrapper-0.3.0.dist-info/top_level.txt
djrest_wrapper-0.3.0.dist-info/RECORD
