Metadata-Version: 2.1
Name: djrest-wrapper
Version: 0.3.0
Summary: Customized Wrapper for Django Rest Framework
Home-page: https://github.com/almohress/drfwrapper
License: MIT
Platform: UNKNOWN
Classifier: Development Status :: 4 - Beta
Classifier: Environment :: Web Environment
Classifier: Intended Audience :: Developers
Classifier: License :: OSI Approved :: MIT License
Classifier: Operating System :: OS Independent
Classifier: Programming Language :: Python :: 3 :: Only
Classifier: Programming Language :: Python :: 3.7
Classifier: Programming Language :: Python :: 3.8
Classifier: Programming Language :: Python :: Implementation :: CPython
Requires-Python: >=3.8
Requires-Dist: Django (>=3.2.5)
Requires-Dist: djangorestframework (>=3.12.4)
